easygui_qt/__init__.py
easygui_qt/calendar_widget.py
easygui_qt/easygui_qt.py
easygui_qt/language_selector.py
easygui_qt/multichoice.py
easygui_qt/multifields.py
easygui_qt/show_text_window.py
easygui_qt/utils.py
easygui_qt/wizard_maker.py
easygui_qt/demos/__init__.py
easygui_qt/demos/_launch_widget.py
easygui_qt/demos/guessing_game.py
easygui_qt/demos/launcher.py
easygui_qt-0.9.3.dist-info/DESCRIPTION.rst
easygui_qt-0.9.3.dist-info/METADATA
easygui_qt-0.9.3.dist-info/RECORD
easygui_qt-0.9.3.dist-info/WHEEL
easygui_qt-0.9.3.dist-info/metadata.json
easygui_qt-0.9.3.dist-info/top_level.txt
